acurl.cpython-38-darwin.so
acurl-1.0.5.dist-info/METADATA
acurl-1.0.5.dist-info/WHEEL
acurl-1.0.5.dist-info/top_level.txt
acurl-1.0.5.dist-info/RECORD
