Metadata-Version: 2.1
Name: acurl
Version: 1.0.5
Summary: An async Curl library.
Home-page: https://github.com/sky-uk/mite/tree/master/acurl
Author: Aaron Ecay
Author-email: aaron.ecay@sky.uk
Maintainer: Sky Identity NFT team
Maintainer-email: matthew.ellis@sky.uk
License: MIT
Classifier: Development Status :: 3 - Alpha
Classifier: Intended Audience :: Developers
Classifier: Programming Language :: Python
Classifier: Programming Language :: Python :: 3
Classifier: Programming Language :: Python :: 3.9
Classifier: Programming Language :: Python :: 3.10
Classifier: Programming Language :: Python :: 3.11
